{
    "clownControl": ["Clown Control", "clown control", "clown", "clowns"],
    "directAttack": ["Direct Attack", "direct attack"],
    "finalCountdown": ["Final Countdown", "final countdown", "countdown"],
    "lockdownBurn": ["Lockdown Burn", "lockdown burn", "stall burn"],
    "drainBurn": ["Drain Burn", "drain burn", "skill burn", "skill drain burn"],
    "chainEnergyBurn": ["Chain Energy Burn", "chain energy burn", "chain energy", "toll burn"],
    "mill": ["Mill", "mill", "lockdown mill", "stall mill", "deck out", "deckout", "deck-out"],
    "pacman": ["P.A.C.M.A.N.", "p.a.c.m.a.n.", "pacman"],
    "wallStall": ["Wall Stall", "wall stall", "wall lockdown"],
    "chaosControl": ["Chaos Control", "chaos control", "cc"],
    "thunderDragonChaosControl": ["Thunder Dragon Chaos Control", "td chaos control", "thunder dragon chaos control", "td cc", "tdcc"],
    "asuraChaosControl": ["Asura Chaos Control", "asura chaos control", "asura chaos", "asura cc"],
    "angelChaosControl": ["Angel Chaos Control", "angel chaos control", "angel chaos", "angel cc", "angel"],
    "skilledWhiteChaosControl": ["Skilled White Chaos Control", "skilled white chaos control", "skilled white magician chaos control", "skilled magician chaos control", "skilled chaos control", "swm chaos control", "skilled white cc", "skilled white magician cc", "skilled magician cc", "skilled cc", "swm cc", "swcc", "swmcc"],
    "chaosTurbo": ["Chaos Turbo", "chaos turbo", "chaos flip turbo", "cft", "ct"],
    "coinToss": ["Coin Toss", "coin toss", "coin flip", "coin control", "coin", "coins"],
    "ectoplasmerControl": ["Ectoplasmer Control", "ectoplasmer control", "ectoplasmer", "malice doll control", "malice doll of demise control", "malice doll of demise", "mdod", "malice doll"],
    "doriado": ["Doriado", "doriado", "doriado control", "elemental mistress doriado", "elemental mistress doriado control", "elemental mistress control", "elemental mistress"],
    "flipControl": ["Flip Control", "flip control", "tsuku lock", "tsuk lock", "flip lock", "mask control", "mask lock", "masks of tsuku", "masks of tsuk", "masks", "mask", "fc"],
    "goatControl": ["Goat Control", "goat control", "goat", "goats", "gc"],
    "burnGoatControl": ["Burn Goat Control", "burn goat control", "burn goat", "burn goats", "burn control"],
    "phoenixGoatControl": ["Phoenix Goat Control", "phoenix goat control", "phoenix goat", "phoenix goats", "phoenix control", "phoenix gc"],
    "spyGoatControl": ["Spy Goat Control", "spy goat control", "spy goat", "spy goats", "spy gc", "spy control"],
    "warriorGoatControl": ["Warrior Goat Control", "warrior goat control", "warrior goat", "warrior goats", "warrior gc", "warrior control"],
    "zombieGoatControl": ["Zombie Goat Control", "zombie goat control", "zombie goat", "zombie goats", "zombie cc"],
    "manticoreControl": ["Manticore Control", "manticore control", "manticore of darkness control", "manticore", "mod control", "modc"],
    "waterManticoreControl": ["Water Manticore Control", "water manticore control", "water manticore", "water manticore of darkness control", "water mod control", "water modc", "wmodc"],
    "monarch": ["Monarch", "monarch", "monarchs", "aggro monarch", "aggro monarchs", "monarch aggro", "brain control monarch", "brain monarch", "bc monarch", "brain control monarchs", "brain monarchs", "bc monarchs"],
    "soulControl": ["Soul Control", "soul control", "soul exchange control", "soul ex control", "soulex", "soul exchange monarch", "soul ex monarch", "soulex monarch"],
    "strikeNinjaMonarch": ["Strike Ninja Monarch", "strike ninja monarch", "strike ninja monarchs", "ninja monarch", "ninja monarchs", "strike monarch", "strike monarchs"],
    "pixieControl": ["Pixie Control", "pixie control", "pixie", "pixies", "pixie knight control", "pixie knight"],
    "relinquishedControl": ["Relinquished Control", "relinquished control", "relinquished", "relinquish", "relinq"],
    "relinquishedChaos": ["Relinquished Chaos", "relinquished chaos", "relinquished chaos control", "relinquish chaos"],
    "spellCounterControl": ["Spell Counter Control", "spell counter control", "spell counter", "spell counters"],
    "aggroBomb": ["Aggro Bomb", "aggro bomb", "aggro burn", "bomb", "panda burn", "panda aggro"],
    "amazon": ["Amazon", "amazon", "amazons", "amazoness", "amazon aggro", "amazoness aggro"],
    "archfiend": ["Archfiend", "archfiend", "archfiends", "archfiend aggro"],
    "armedDragon": ["Armed Dragon", "armed dragon", "armed dragon aggro"],
    "bazooReturn": ["Bazoo Return", "bazoo return", "bazoo"],
    "beatdown": ["Beatdown", "beatdown", "beat", "generic beatdown", "zoo", "zoo aggro", "zoo beatdown"],
    "beastdown": ["Beastdown", "beastdown", "beast beatdown", "beast beat", "beasts", "beast"],
    "chaosBeatdown": ["Chaos Beatdown", "chaos beatdown", "chaos beat", "chaos aggro"],
    "darkBeatdown": ["Dark Beatdown", "dark beatdown", "dark beat", "dark", "dark aggro"],
    "drainBeatdown": ["Drain Beatdown", "drain beatdown", "drain beat", "skill drain beatdown", "skill beat", "skill drain aggro", "skill aggro", "drain aggro"],
    "earthBeatdown": ["Earth Beatdown", "earth beatdown", "earth beat", "earth", "earth aggro"],
    "elementalBeatdown": ["Elemental Beatdown", "elemental beatdown", "elemental beat", "elemental", "element beatdown", "element beat", "element", "elements"],
    "fairyBeatdown": ["Fairy Beatdown", "fairy beatdown", "fairy beat", "fairy", "fairy aggro"],
    "fireBeatdown": ["Fire Beatdown", "fire beatdown", "fire beat", "fire", "fire aggro"],
    "lightBeatdown": ["Light Beatdown", "light beatdown", "light beat", "light", "light aggro"],
    "wanghuBeatdown": ["Wanghu Beatdown", "wanghu beatdown", "wanghu beat", "wanghu", "wanghu aggro"],
    "windBeatdown": ["Wind Beatdown", "wind beatdown", "wind beat", "wind", "wind aggro"],
    "chaosRecruiter": ["Chaos Recruiter", "chaos recruiter", "recruiter chaos", "chaos recruiters"],
    "chaosReturn": ["Chaos Return", "chaos return"],
    "dragon": ["Dragon", "dragon", "dragon beatdown", "dragon beat", "dragon aggro", "dragons"],
    "blueEyesDragon": ["Blue-Eyes Dragon", "blue-eyes dragon", "blue eyes dragon", "blue-eyes", "blue-eyes beatdown", "blue-eyes beat", "blue-eyes aggro", "blue eyes beatdown", "blue eyes beat", "blue eyes aggro"],
    "fluteDragon": ["Flute Dragon", "flute dragon", "flute dragon beatdown", "flute dragon beat", "flute dragon aggro", "flute dragons"],
    "horusDragon": ["Horus Dragon", "horus dragon", "horus dragon beatdown", "horus dragon beat", "horus dragon aggro", "horus dragons"],
    "redEyesDragon": ["Red-Eyes Dragon", "red-eyes dragon", "red eyes dragon", "red-eyes", "red-eyes beatdown", "red-eyes beat", "red-eyes aggro", "red eyes beatdown", "red eyes beat", "red eyes aggro"],
    "elementalHERO": ["Elemental HERO", "elemental hero", "elemental heros", "elemental heroes", "hero", "heros", "heroes", "e-hero", "e-heros", "e-heroes", "ehero", "eheros", "eheroes"],
    "emissaryAggro": ["Emissary Aggro", "emissary aggro", "emmissary aggro", "emissary beatdown", "emmissary beatdown", "emissary beat", "emmissary beat", "emissary", "emmissary", "emissary of the afterlife", "emmissary of the afterlife", "eota aggro", "eota beatdown", "eota beat", "eota"],
    "fiendAggro": ["Fiend Aggro", "fiend aggro", "fiend beatdown", "fiend beat", "fiend", "fiends"],
    "gravekeeper": ["Gravekeeper", "gravekeeper", "gravekeeper\"s", "gravekeepers", "gk", "gks"],
    "grenMaju": ["Gren Maju", "gren maju", "gren maju da eiza", "gren maju aggro", "gren maju beatdown", "gren maju beat", "maju", "maju aggro", "maju beatdown", "maju beat"],
    "harpie": ["Harpie", "harpie", "harpies", "harpie lady", "harpie ladies", "harpie aggro", "harpie beatdown", "harpie beat", "harpie lady aggro", "harpie lady beatdown", "harpie lady beat"],
    "horus": ["Horus", "horus", "horus beatdown", "horus beat", "horus aggro", "horus"],
    "machine": ["Machine", "machine", "machines", "machine otk"],
    "xyzMachine": ["XYZ Machine", "xyz machine", "xyz machines", "xyz"],
    "ninjaAggro": ["Ninja Aggro", "ninja aggro", "ninja", "ninjas"],
    "paladinOfWhiteDragon": ["Paladin of White Dragon", "paladin of white dragon", "paladin"],
    "ratbox": ["Ratbox", "ratbox", "rat box", "rat"],
    "silentSwordsman": ["Silent Swordsman", "silent swordsman"],
    "spellCancellerAggro": ["Spell Canceller Aggro", "spell canceller aggro", "spell canceller"],
    "spirit": ["Spirit", "spirit", "spirits"],
    "strikeNinjaReturn": ["Strike Ninja Return", "strike ninja return", "strike ninja"],
    "toon": ["Toon", "toon", "toons"],
    "ultimateInsect": ["Ultimate Insect", "ultimate insect"],
    "vanillaAggro": ["Vanilla Aggro", "vanilla aggro", "vanilla", "vanillas"],
    "waterVanillaAggro": ["Water Vanilla Aggro", "water vanilla aggro", "water vanilla", "water vanillas", "vanilla water", "vanilla waters"],
    "warrior": ["Warrior", "warrior", "anti-meta warrior", "warriors", "warrior aggro", "anti meta warrior","antimeta warrior", "anti-meta warriors", "anti meta warriors","antimeta warriors"],
    "dnaWarrior" : ["DNA Warrior", "dna warrior", "dna warriors", "dna warrior aggro", "dna warrior beatdown", "dna warrior beat"],
    "gearfriedWarrior": ["Gearfried Warrior", "gearfriend warrior", "gearfried warriors", "gearfried", "gearfriend aggro", "gearfried beatdown", "gearfried beat"],
    "gearfriedWanghu": ["Gearfried Wanghu", "gearfriend wanghu", "gearfried tiger", "wanghu gearfried", "tiger gearfried", "wanghu gearfried stun", "tiger gearfried stun", "gearfried wanghu stun", "gearfried tiger stun", "wanghu gearfried aggro", "tiger gearfried aggro", "gearfried wanghu aggro", "gearfried tiger aggro", "wanghu gearfried beatdown", "tiger gearfried beatdown", "gearfried wanghu beatdown", "gearfried tiger beatdown", "wanghu gearfried beat", "tiger gearfried beat", "gearfried wanghu beat", "gearfried tiger beat"],
    "chaosWarrior" : ["Chaos Warrior", "chaos warrior", "chaos warriors", "chaos warrior aggro", "chaos warrior beatdown", "chaos warrior beat", "warrior chaos"],
    "meanaeWarrior" : ["Meanae Warrior", "meanae warrior", "meanae warriors", "meanae warrior aggro", "meanae warrior beatdown", "meanae warrior beat", "dark scorpion", "dark scorpions", "dark scorpion gang", "dark scorp", "dark scrops", "dark scorpion aggro", "dark scorpion beatdown", "dark scorpion beat", "scorpion", "scorpions"],
    "wanghuWarrior" : ["Wanghu Warrior", "wanghu warrior", "wanghu warriors", "wanghu warrior aggro", "wanghu warrior beatdown", "wanghu warrior beat", "tiger warrior stun", "tiger warrior", "tiger warriors", "tiger warrior aggro", "tiger warrior beatdown", "tiger warrior beat", "tiger warrior stun"],
    "waterAggro": ["Water Aggro", "water aggro", "water", "waters", "water beatdown", "water beat"],
    "orcaWaterAggro": ["Orca Water Aggro", "orca water aggro", "orca water", "orca aggro", "orca beatdown", "orca beat", "orca water beatdown", "orca water beat"],
    "zombie": ["Zombie", "zombie", "zombies", "zombie beatdown", "zombie aggro", "zombie beat"],
    "cardOfSafeReturnZombie": ["Card of Safe Return Zombie", "card of safe return zombie", "card of safe return zombies", "cosr zombie beatdown", "cosr zombies"],
    "drainZombie": ["Drain Zombie", "drain zombie", "drain zombies", "skill drain zombie", "skill drain zombies", "skill zombie", "skill zombies", "zombie skill"],
    "skullServantZombie": ["Skull Servant Zombie", "skull servant zombie", "skull servant zombies", "skull servant"],
    "asuraOTK": ["Asura OTK", "asura otk", "big bang asura otk", "big bang shot asura otk", "bbs asura otk", "big bang asura", "big bang shot asura", "bbs asura"],
    "benKeiOTK": ["Ben-Kei OTK", "ben-kei otk", "ben kei", "ben-kei", "ben kei otk", "ben-kei combo", "ben kei combo"],
    "blastingTheRuins": ["Blasting the Ruins", "blasting the ruins", "blasting the ruins otk", "ruins otk", "ruins"],
    "bugrothOTK": ["Bugroth OTK", "bugroth otk", "bugroth", "amphibious bugroth otk", "amphibious bugroth", "amphibious bugroth mk3 otk", "amphibious bugroth mk3", "amphibious bugroth mk-3 otk", "amphibious bugroth mk-3"],
    "chaosGreed": ["Chaos Greed", "chaos greed", "banish", "banish combo"],
    "stein": ["Cyber-Stein OTK", "cyber-stein otk", "stein otk", "stein", "cyber-stein", "cyber stein", "cyber-stein otk", "cyber stein otk"],
    "destinyBoard": ["Destiny Board", "destiny board", "destiny board combo", "destiny", "destiny combo"],
    "dimensionFusionTurbo": ["Dimension Fusion Turbo", "dimension fusion turbo", "dimension fusion otk", "dimension fusion", "dft", "bazoo dimension fusion turbo", "bazoo dft", "bazoo dimension fusion otk", "bazoo dimension fusion"],
    "dragonDimensionFusionTurbo": ["Dragon Dimension Fusion Turbo", "dragon dimension fusion turbo", "dragon dimension fusion otk", "dragon dimension fusion", "dragon dft", "dragon fusion turbo", "dragon turbo", "dimension dragon", "dimension dragon turbo", "dimension dragon otk"],
    "earthDimensionFusionTurbo": ["Earth Dimension Fusion Turbo", "dragon dimension fusion turbo", "dragon dimension fusion otk", "dragon dimension fusion", "dragon dft", "dragon fusion turbo", "dragon turbo", "dimension dragon", "dimension dragon turbo", "dimension dragon otk"],
    "fireDimensionFusionTurbo": ["Fire Dimension Fusion Turbo", "fire dimension fusion turbo", "fire dimension fusion otk", "fire dimension fusion", "fire dft", "fire fusion turbo", "fire turbo", "dimension fire", "dimension fire turbo", "dimension fire otk"],
    "lightDimensionFusionTurbo": ["Light Dimension Fusion Turbo", "light dimension fusion turbo", "light dimension fusion otk", "light dimension fusion", "light dft", "light fusion turbo", "light turbo", "dimension light", "dimension light turbo", "dimension light otk"],
    "machineDimensionFusionTurbo": ["Machine Dimension Fusion Turbo", "machine dimension fusion turbo", "machine dimension fusion otk", "machine dimension fusion", "machine dft", "machine fusion turbo", "machine turbo", "dimension machine", "dimension machine turbo", "dimension machine otk"],
    "emptyJar": ["Empty Jar", "empty jar", "e-jar", "e jar", "ejar", "empty jar ftk", "empty jar combo"],
    "exodia": ["Exodia", "exodia", "exodia ftk"],
    "appropriateExodia": ["Appropriate Exodia", "appropriate exodia", "appropriate exodia ftk"],
    "vanillaExodia": ["Vanilla Exodia", "vanilla exodia", "vanilla exodia ftk"],
    "vanillaDragonExodia": ["Vanilla Dragon Exodia", "vanilla dragon exodia", "vanilla dragon exodia ftk"],
    "fusionGateTurbo": ["Fusion Gate Turbo", "fusion gate turbo", "fusion gate otk", "fusion gate", "fusion gate combo", "fgt"],
    "heavySlump": ["Heavy Slump", "heavy slump", "heavy slump combo", "slump", "slumo combo"],
    "chaosSlump": ["Chaos Slump", "chaos slump", "chaos heavy slump combo", "chaos heavy slump", "chaos heavy slumo combo"],
    "hinoKaguTsuchi": ["Hino-Kagu-Tsuchi", "hino-kagu-tsuchi", "hino kagu tsuchi", "hino-kagu tsuchi", "hino-kagu", "hino kagu"],
    "hugeRevolution": ["Huge Revolution", "huge revolution", "the huge revolution", "huge revolution otk", "huge revolution turbo", "revolution otk", "revolution turbo", "revolution"],
    "lastTurn": ["Last Turn", "last turn", "lt"],
    "libraryFTK": ["Library FTK", "library ftk", "library"],
    "mahaVailo": ["Maha Vailo", "maha vailo", "maha", "vailo"],
    "mokeyMokeySmackdown": ["Mokey Mokey Smackdown", "mokey mokey smackdown", "mokey mokey", "smackdown"],
    "mazeraDeVilla": ["Mazera DeVille", "mazera deville", "mazera", "mazera deville combo", "mazera combo"],
    "necromancerOTK": ["Necromancer OTK", "necromancer otk", "necromancer"],
    "neoDaedalus": ["Neo-Daedalus", "neo-daedalus otk", "neo daedalus"],
    "ojama": ["Ojama", "ojama", "ojamas"],
    "pyramidOfLight": ["Pyramid of Light", "pyramid of light", "pyramid"],
    "reasoningGateTurbo": ["Reasoning Gate Turbo", "reasoning gate turbo", "reasoning gate", "reason gate turbo", "reason gate", "rgt"],
    "thunderDragonReasoningGateTurbo": ["Reasoning Gate Turbo", "thunder dragon reasoning gate turbo", "thunder dragon reasoning gate", "thunder dragon reason gate turbo", "thunder dragon reason gate", "thunder dragon rgt", "thunder dragon gate", "td gate", "td reasoning gate turbo", "td reasoning gate", "td reason gate turbo", "td reason gate", "td rgt", "tdrgt"],
    "venusReasoningGateTurbo": ["Venus Reasoning Gate Turbo", "venus reasoning gate turbo", "venus reasoning gate", "venus reason gate turbo", "venus reason gate", "venus rgt", "venus gate", "vrgt"],
    "waterReasoningGateTurbo": ["Water Reasoning Gate Turbo", "water reasoning gate turbo", "water reasoning gate", "water reason gate turbo", "water reason gate", "water rgt", "water gate", "wrgt"],
    "rescueCat": ["Rescue Cat", "rescue cat", "rescue cat otk", "cat", "cat otk"],
    "reversalQuizOTK": ["Reversal Quiz OTK", "reversal quiz otk", "reversal quiz", "quiz", "quiz otk"],
    "shinato": ["Shinato", "shinato", "shinato king of a higher plane", "shinato otk", "shinato combo", "quiz otk"],
    "speedBurn": ["Speed Burn", "speed burn", "turbo burn", "jar burn"],
    "economicsFTK": ["Economics FTK", "economics ftk", "economics", "mass driver ftk", "mass driver"],
    "darkMasterZorc": ["Dark Master Zorc", "dark master zorc", "dark master - zorc", "zorc"],
    "other": ["Other"]
}